lightface/LightFace.py
lightface/__init__.py
lightface-0.0.1.dist-info/LICENSE
lightface-0.0.1.dist-info/METADATA
lightface-0.0.1.dist-info/WHEEL
lightface-0.0.1.dist-info/top_level.txt
lightface-0.0.1.dist-info/RECORD
