Metadata-Version: 2.1
Name: lightface
Version: 0.0.1
Summary: A lightweight deep face recognition framework
Home-page: https://github.com/serengil/lightface
Author: Sefik Ilkin Serengil
Author-email: serengil@gmail.com
License: UNKNOWN
Platform: UNKNOWN
Classifier: Programming Language :: Python :: 3
Classifier: License :: OSI Approved :: MIT License
Classifier: Operating System :: OS Independent
Requires-Python: >=3.5.5
Requires-Dist: numpy (>=1.14.0)
Requires-Dist: pandas (>=0.23.4)
